setup.py
topical/__init__.py
topical.egg-info/PKG-INFO
topical.egg-info/SOURCES.txt
topical.egg-info/dependency_links.txt
topical.egg-info/pbr.json
topical.egg-info/requires.txt
topical.egg-info/top_level.txt
topical/codecs/__init__.py
topical/codecs/multi.py
topical/codecs/registered_avro.py
topical/codecs/zlib_codec.py