Metadata-Version: 1.0
Name: topical
Version: 0.0.4
Summary: Topic-oriented API for producing and consuming Kafka streams with support for pluggable codecs
Home-page: http://github.com/gamechanger/topical
Author: Tom Leach
Author-email: tom@gc.com
License: MIT
Keywords: kafka topic encoding decoding streams python
Platform: UNKNOWN
